{
  "version": 2,
  "extractor": "pdffigures2",
  "figures": [
    {
      "url": "assets/figures/arxiv/2604.11275v1/fig-001.webp",
      "caption": "Table 4.1: Performance on NAVER-Seoul Dataset (South Korea) and METR-LA dataset (USA).",
      "page": 7,
      "index": 1,
      "width": 862,
      "height": 457
    },
    {
      "url": "assets/figures/arxiv/2604.11275v1/fig-002.webp",
      "caption": "Figure 4.1: Forecasting error (MAE) across increasing prediction horizons on METR-LA, NAVER-Seoul, and Air Quality datasets. ST-Sheaf exhibits slower error accumulation over longer horizons compared to strong baselines.",
      "page": 7,
      "index": 2,
      "width": 922,
      "height": 244
    },
    {
      "url": "assets/figures/arxiv/2604.11275v1/fig-003.webp",
      "caption": "Table 5.1: Performance on Molene weather dataset (France), Air Quality dataset (China) in MAE and PEMS04, PEMS08 traffic datasets (USA).",
      "page": 7,
      "index": 3,
      "width": 1016,
      "height": 242
    },
    {
      "url": "assets/figures/arxiv/2604.11275v1/fig-004.webp",
      "caption": "Figure 5.2: Case study of spatiotemporal dependency modeling on METR-LA test set: A congestion event originating at sensor 36 propagates to affect sensor 62 afterwards. The ST-Sheaf model captures this cascade effect in the prediction, while baseline methods fail to predict the induced slowdown.",
      "page": 8,
      "index": 4,
      "width": 486,
      "height": 263
    },
    {
      "url": "assets/figures/arxiv/2604.11275v1/fig-005.webp",
      "caption": "Figure 5.1: Oversmoothing Analysis: ST-Sheaf GNN diffusion vs. traditional GCN diffusion. The y-axis is the average Euclidean Distance of hidden representation between Connected nodes at each layer.",
      "page": 8,
      "index": 5,
      "width": 465,
      "height": 276
    },
    {
      "url": "assets/figures/arxiv/2604.11275v1/fig-006.webp",
      "caption": "Figure 3.1: Overview of the proposed ST-Sheaf GNN. Multivariate time-series signals on a graph are first encoded with multi-head attention to capture temporal dependencies. The resulting representations are projected into a sheaf space, where dynamic restriction maps are computed. Sheaf diffusion layers propagate information by preserving local node distinct representation. The diffused features are finally decoded by an MLP to produce node-level forecasts.",
      "page": 4,
      "index": 6,
      "width": 957,
      "height": 400
    },
    {
      "url": "assets/figures/arxiv/2604.11275v1/fig-007.webp",
      "caption": "Table 5.4: Ablation Studies on the effect of each of the model components on different datasets in MAE. For Molene, we select (step-1, 3, 5 as H1, H2, H3).",
      "page": 9,
      "index": 7,
      "width": 469,
      "height": 285
    },
    {
      "url": "assets/figures/arxiv/2604.11275v1/fig-008.webp",
      "caption": "Figure 3.2: Sheaf graph representation with learned dynamic restriction maps. Each node is associated with a vertex stalk and each edge is associated with an edge stalk. Restriction maps define the relation between vertex stalks and edge stalks.",
      "page": 5,
      "index": 8,
      "width": 406,
      "height": 323
    }
  ]
}